<?xml version="1.0"?>
<?xml-stylesheet type='text/xsl' href='MessageLog.xsl'?>
<Log FirstSessionID="1" LastSessionID="2"><Message Date="2008-04-12" Time="10:50:30" DateTime="2008-04-12T08:50:30.421Z" SessionID="1"><From><User FriendlyName="Martin"/></From><To><User FriendlyName="Scox"/></To><Text Style="font-family:MS Shell Dlg; color:#000000; ">Hej hej!</Text></Message><Message Date="2008-04-12" Time="10:50:45" DateTime="2008-04-12T08:50:45.390Z" SessionID="1"><From><User FriendlyName="Martin"/></From><To><User FriendlyName="Scox"/></To><Text Style="font-family:MS Shell Dlg; color:#000000; ">Vi tittar föbi en sväng under eftermiddagen.</Text></Message><Message Date="2008-04-12" Time="11:15:57" DateTime="2008-04-12T09:15:57.203Z" SessionID="1"><From><User FriendlyName="Scox"/></From><To><User FriendlyName="Martin"/></To><Text Style="font-family:MS Shell Dlg; color:#000000; ">finemang</Text></Message><Message Date="2008-04-16" Time="21:57:03" DateTime="2008-04-16T19:57:03.428Z" SessionID="2"><From><User FriendlyName="Martin"/></From><To><User FriendlyName="Scox"/></To><Text Style="font-family:MS Shell Dlg; color:#000000; ">tjenare! Tackar för senast.</Text></Message><Message Date="2008-04-16" Time="21:57:27" DateTime="2008-04-16T19:57:27.383Z" SessionID="2"><From><User FriendlyName="Scox"/></From><To><User FriendlyName="Martin"/></To><Text Style="font-family:MS Shell Dlg; color:#000000; ">tack för att ni kom .:)</Text></Message></Log>
